[
  {
    "prize": "best_film",
    "year": 1965,
    "th": 3,
    "film_name_zh": "養鴨人家",
    "film_name_en": "Beautiful Duckling",
    "atmovie_link": "",
    "imdb_link": "https://www.imdb.com/title/tt01345532/",
    "movie_id": "tt01345532"
  },
  {
    "prize": "best_film",
    "year": 1988,
    "th": 25,
    "film_name_zh": "七小福",
    "film_name_en": "Painted Faces",
    "atmovie_link": "http://app2.atmovies.com.tw/film/fPhk30095937/",
    "imdb_link": "https://www.imdb.com/title/tt0095937",
    "movie_id": "tt0095937",
    "poster_path": "/7zCDRUo1lQdKReSchi3MzrMGCyU.jpg"
  },
  {
    "prize": "best_film",
    "year": 1966,
    "th": 4,
    "film_name_zh": "西施",
    "film_name_en": "Xi shi",
    "atmovie_link": "",
    "imdb_link": "https://www.imdb.com/title/tt0311305/",
    "movie_id": "tt0311305",
    "poster_path": null
  },
  {
    "prize": "best_film",
    "year": 1991,
    "th": 28,
    "film_name_zh": "牯嶺街少年殺人事件",
    "film_name_en": "A Brighter Summer Day",
    "atmovie_link": "http://app2.atmovies.com.tw/film/fEcmb9091442/",
    "imdb_link": "https://www.imdb.com/title/tt0101985",
    "movie_id": "tt0101985",
    "poster_path": "/rDZ2mNQkZrnSzHPLQ7SzhzgCSoj.jpg"
  },
  {
    "prize": "best_film",
    "year": 1982,
    "th": 19,
    "film_name_zh": "辛亥雙十",
    "film_name_en": "The Battle for the Republic of China",
    "atmovie_link": "http://app2.atmovies.com.tw/film/fVcmb4041256",
    "imdb_link": "https://www.imdb.com/title/tt00083346/",
    "movie_id": "tt00083346"
  },
  {
    "prize": "best_film",
    "year": 1984,
    "th": 21,
    "film_name_zh": "老莫的第二個春天",
    "film_name_en": "Second Spring of Mr",
    "atmovie_link": "http://app2.atmovies.com.tw/film/fXcmb8081026/",
    "imdb_link": "https://www.imdb.com/title/tt0183390",
    "movie_id": "tt0183390",
    "poster_path": null
  },
  {
    "prize": "best_film",
    "year": 1985,
    "th": 22,
    "film_name_zh": "我這樣過了一生",
    "film_name_en": "Kuei",
    "atmovie_link": "http://app2.atmovies.com.tw/film/fJcmb7071169/",
    "imdb_link": "https://www.imdb.com/title/tt0092231",
    "movie_id": "tt0092231",
    "poster_path": "/t7QKMkMzDC5BrzF5VQb8f9lTnfu.jpg"
  },
  {
    "prize": "best_film",
    "year": 1980,
    "th": 17,
    "film_name_zh": "早安台北",
    "film_name_en": "Good Morning, Taipei",
    "atmovie_link": "http://app2.atmovies.com.tw/film/fYcmb4040985",
    "imdb_link": "https://www.imdb.com/title/tt00314939/",
    "movie_id": "tt00314939"
  },
  {
    "prize": "best_film",
    "year": 1972,
    "th": 10,
    "film_name_zh": "秋決",
    "film_name_en": "Execution in Autumn",
    "atmovie_link": "http://app2.atmovies.com.tw/film/fFcmb2021755",
    "imdb_link": "https://www.imdb.com/title/tt01033618/",
    "movie_id": "tt01033618"
  },
  {
    "prize": "best_film",
    "year": 1975,
    "th": 12,
    "film_name_zh": "吾土吾民",
    "film_name_en": "Land of the Undaunted",
    "atmovie_link": "",
    "imdb_link": "https://www.imdb.com/title/tt0314902",
    "movie_id": "tt0314902",
    "poster_path": "/zHLuj1jyU0yM6g2HWXQsQWlsU6l.jpg"
  },
  {
    "prize": "best_film",
    "year": 2002,
    "th": 39,
    "film_name_zh": "美麗時光",
    "film_name_en": "The Best Of Times",
    "atmovie_link": "http://app2.atmovies.com.tw/film/fbtw40309606/",
    "imdb_link": "https://www.imdb.com/title/tt0333902",
    "movie_id": "tt0333902",
    "poster_path": "/ltyQy1kBuQfmNWwhme1kPtM6P3S.jpg"
  },
  {
    "prize": "best_film",
    "year": 1981,
    "th": 18,
    "film_name_zh": "假如我是真的",
    "film_name_en": "If I Were for Real",
    "atmovie_link": "http://app2.atmovies.com.tw/film/fRcmb6062155",
    "imdb_link": "https://www.imdb.com/title/tt00289112/",
    "movie_id": "tt00289112"
  },
  {
    "prize": "best_film",
    "year": 1977,
    "th": 14,
    "film_name_zh": "筧橋英烈傳",
    "film_name_en": "Heroes of the Eastern Skies",
    "atmovie_link": "",
    "imdb_link": "https://www.imdb.com/title/tt00184567/",
    "movie_id": "tt00184567"
  },
  {
    "prize": "best_film",
    "year": 2006,
    "th": 43,
    "film_name_zh": "父子",
    "film_name_en": "After This Our Exile",
    "atmovie_link": "http://app2.atmovies.com.tw/film/fahk20768114/",
    "imdb_link": "https://www.imdb.com/title/tt0768114",
    "movie_id": "tt0768114",
    "poster_path": "/iQOtB5mD1FcXtj8xFWKehzpOB1M.jpg"
  },
  {
    "prize": "best_film",
    "year": 1994,
    "th": 31,
    "film_name_zh": "愛情萬歲",
    "film_name_en": "Vive l'Amour",
    "atmovie_link": "http://app2.atmovies.com.tw/film/fOcmb4042729/",
    "imdb_link": "https://www.imdb.com/title/tt0109066",
    "movie_id": "tt0109066",
    "poster_path": "/kzT7WvRaolavasYSWnaefGUx8Wi.jpg"
  },
  {
    "prize": "best_film",
    "year": 1979,
    "th": 16,
    "film_name_zh": "小城故事",
    "film_name_en": "The Story of A Small Town",
    "atmovie_link": "http://app2.atmovies.com.tw/film/fVcmb4040412",
    "imdb_link": "https://www.imdb.com/title/tt00314907/",
    "movie_id": "tt00314907"
  },
  {
    "prize": "best_film",
    "year": 1962,
    "th": 1,
    "film_name_zh": "星星月亮太陽",
    "film_name_en": "Sun, Moon and Star",
    "atmovie_link": "",
    "imdb_link": "https://www.imdb.com/title/tt00211753/",
    "movie_id": "tt00211753"
  },
  {
    "prize": "best_film",
    "year": 2001,
    "th": 38,
    "film_name_zh": "榴槤飄飄",
    "film_name_en": "Durian Durian",
    "atmovie_link": "http://app2.atmovies.com.tw/film/fDatm0894197/",
    "imdb_link": "https://www.imdb.com/title/tt0255327",
    "movie_id": "tt0255327",
    "poster_path": "/dY6qtXbIMTNoo6fbdvoKmuuN4Kl.jpg"
  },
  {
    "prize": "best_film",
    "year": 1987,
    "th": 24,
    "film_name_zh": "稻草人",
    "film_name_en": "Strawman",
    "atmovie_link": "http://app2.atmovies.com.tw/film/fstw30092829/",
    "imdb_link": "https://www.imdb.com/title/tt0092829",
    "movie_id": "tt0092829",
    "poster_path": "/1TS4ZCLFzmNUFaAIuLU9gygpm8Q.jpg"
  },
  {
    "prize": "best_film",
    "year": 1999,
    "th": 36,
    "film_name_zh": "千言萬語",
    "film_name_en": "Ordinary Heroes",
    "atmovie_link": "http://app2.atmovies.com.tw/film/fOatm0884147/",
    "imdb_link": "https://www.imdb.com/title/tt0189954",
    "movie_id": "tt0189954",
    "poster_path": "/gCdAeYNtN8wKidupd9wj8GQ8P9o.jpg"
  },
  {
    "prize": "best_film",
    "year": 1971,
    "th": 9,
    "film_name_zh": "緹縈",
    "film_name_en": "The Story of Tin-Ying",
    "atmovie_link": "http://app2.atmovies.com.tw/film/fWcmb2023094/",
    "imdb_link": "https://www.imdb.com/title/tt0067797/",
    "movie_id": "tt0067797",
    "poster_path": "/qvGEE5aVLUqGUUcAVHDrtbcBs7I.jpg"
  },
  {
    "prize": "best_film",
    "year": 2003,
    "th": 40,
    "film_name_zh": "無間道",
    "film_name_en": "Infernal Affairs",
    "atmovie_link": "http://app2.atmovies.com.tw/film/fihk30610065/",
    "imdb_link": "https://www.imdb.com/title/tt0338564",
    "movie_id": "tt0338564",
    "poster_path": "/gix9thDBXfjJ8M7rYbihqbQGBcP.jpg"
  },
  {
    "prize": "best_film",
    "year": 1976,
    "th": 13,
    "film_name_zh": "梅花",
    "film_name_en": "Victory",
    "atmovie_link": "http://app2.atmovies.com.tw/film/fAcmb2022346",
    "imdb_link": "https://www.imdb.com/title/tt00195050/",
    "movie_id": "tt00195050"
  },
  {
    "prize": "best_film",
    "year": 2007,
    "th": 44,
    "film_name_zh": "色，戒",
    "film_name_en": "Lust",
    "atmovie_link": "http://app2.atmovies.com.tw/film/flen30808357/",
    "imdb_link": "https://www.imdb.com/title/tt0808357",
    "movie_id": "tt0808357",
    "poster_path": "/zkkkv85ljiJcIee8FNiEZdDHQMl.jpg"
  },
  {
    "prize": "best_film",
    "year": 2015,
    "th": 52,
    "film_name_zh": "刺客聶隱娘",
    "film_name_en": "The Assassin",
    "atmovie_link": "http://app2.atmovies.com.tw/film/fatw31123365/",
    "imdb_link": "https://www.imdb.com/title/tt3508840",
    "movie_id": "tt3508840",
    "poster_path": "/10RcGMfzg2lIW1aLcR4ILfNbHK2.jpg"
  },
  {
    "prize": "best_film",
    "year": 2020,
    "th": 57,
    "film_name_zh": "消失的情人節",
    "film_name_en": "My Missing Valentins",
    "atmovie_link": "http://app2.atmovies.com.tw/film/fdkr65238137/",
    "imdb_link": "https://www.imdb.com/title/tt13105824",
    "movie_id": "tt13105824",
    "poster_path": "/qzzoKV9hVVKVTR5hYlAt2SCn3mz.jpg"
  },
  {
    "prize": "best_film",
    "year": 1990,
    "th": 27,
    "film_name_zh": "滾滾紅塵",
    "film_name_en": "Red Dust",
    "atmovie_link": "http://app2.atmovies.com.tw/film/fEatm0864102/",
    "imdb_link": "https://www.imdb.com/title/tt0099719",
    "movie_id": "tt0099719",
    "poster_path": "/hzDvm4pbYUSxXRMFIR6tIyzXaCG.jpg"
  },
  {
    "prize": "best_film",
    "year": 2012,
    "th": 49,
    "film_name_zh": "神探亨特張",
    "film_name_en": "Detective Hunter Zhang",
    "atmovie_link": "http://app2.atmovies.com.tw/film/fdcn53757616/",
    "imdb_link": "https://www.imdb.com/title/tt2273470",
    "movie_id": "tt2273470",
    "poster_path": "/3o2nk6ZEiuQL7jAx83DFYJUChk6.jpg"
  },
  {
    "prize": "best_film",
    "year": 1978,
    "th": 15,
    "film_name_zh": "汪洋中的一條船",
    "film_name_en": "He Never Gives Up",
    "atmovie_link": "http://app2.atmovies.com.tw/film/fJatm0867010",
    "imdb_link": "https://www.imdb.com/title/tt00079277/",
    "movie_id": "tt00079277"
  },
  {
    "prize": "best_film",
    "year": 1970,
    "th": 8,
    "film_name_zh": "家在台北",
    "film_name_en": "Home Sweet Home",
    "atmovie_link": "http://app2.atmovies.com.tw/film/fRcmb4041894",
    "imdb_link": "https://www.imdb.com/title/tt00978620/",
    "movie_id": "tt00978620"
  },
  {
    "prize": "best_film",
    "year": 1986,
    "th": 23,
    "film_name_zh": "恐怖份子",
    "film_name_en": "The Terrorizers",
    "atmovie_link": "http://app2.atmovies.com.tw/film/fDcmb4041907/",
    "imdb_link": "https://www.imdb.com/title/tt0091355",
    "movie_id": "tt0091355",
    "poster_path": "/xO8X6GOPJsurTu3xvxFWqJJlJNa.jpg"
  },
  {
    "prize": "best_film",
    "year": 2009,
    "th": 46,
    "film_name_zh": "不能沒有你",
    "film_name_en": "Cannot Live Without You",
    "atmovie_link": "http://app2.atmovies.com.tw/film/fntw59710062/",
    "imdb_link": "https://www.imdb.com/title/tt1456584",
    "movie_id": "tt1456584",
    "poster_path": "/soWD4EVuJGXDWyY7xVC1mJhkdOZ.jpg"
  },
  {
    "prize": "best_film",
    "year": 2019,
    "th": 56,
    "film_name_zh": "陽光普照",
    "film_name_en": "A Sun",
    "atmovie_link": "http://app2.atmovies.com.tw/film/fscn43857002/",
    "imdb_link": "https://www.imdb.com/title/tt10883506",
    "movie_id": "tt10883506",
    "poster_path": "/tY8w7eOiNwtbiVfPmTxspkt46bW.jpg"
  },
  {
    "prize": "best_film",
    "year": 1989,
    "th": 26,
    "film_name_zh": "三個女人的故事",
    "film_name_en": "Full Moon in New York",
    "atmovie_link": "http://app2.atmovies.com.tw/film/fNatm0857010/",
    "imdb_link": "https://www.imdb.com/title/tt0098187",
    "movie_id": "tt0098187",
    "poster_path": null
  },
  {
    "prize": "best_film",
    "year": 2004,
    "th": 41,
    "film_name_zh": "可可西里",
    "film_name_en": "Kekexili",
    "atmovie_link": "http://app2.atmovies.com.tw/film/fkcn40386651/",
    "imdb_link": "https://www.imdb.com/title/tt0386651",
    "movie_id": "tt0386651",
    "poster_path": "/cPwpHuwvKthGXD0VXwCnPdUfpZn.jpg"
  },
  {
    "prize": "best_film",
    "year": 1967,
    "th": 5,
    "film_name_zh": "我女若蘭",
    "film_name_en": "Orchids and My Love",
    "atmovie_link": "http://app2.atmovies.com.tw/film/fJcmb4041136",
    "imdb_link": "https://www.imdb.com/title/tt00185582/",
    "movie_id": "tt00185582"
  },
  {
    "prize": "best_film",
    "year": 1997,
    "th": 34,
    "film_name_zh": "甜蜜蜜",
    "film_name_en": "Comrades Almost a Love Story",
    "atmovie_link": "http://app2.atmovies.com.tw/film/fWatm0853019/",
    "imdb_link": "https://www.imdb.com/title/tt0117905",
    "movie_id": "tt0117905",
    "poster_path": "/hjlRaJEa8zuN72LmMATQ3FcCTb0.jpg"
  },
  {
    "prize": "best_film",
    "year": 1998,
    "th": 35,
    "film_name_zh": "天浴",
    "film_name_en": "Tian yu",
    "atmovie_link": "http://app2.atmovies.com.tw/film/fWatm0882003/",
    "imdb_link": "https://www.imdb.com/title/tt0115005",
    "movie_id": "tt0115005",
    "poster_path": "/oJ2kQmP4doYE4ErUvpbUXAdu5Ei.jpg"
  },
  {
    "prize": "best_film",
    "year": 2005,
    "th": 42,
    "film_name_zh": "功夫",
    "film_name_en": "Kung Fu Hustle",
    "atmovie_link": "http://app2.atmovies.com.tw/film/fken20373074/",
    "imdb_link": "https://www.imdb.com/title/tt0373074",
    "movie_id": "tt0373074",
    "poster_path": "/exbyTbrvRUDKN2mcNEuVor4VFQW.jpg"
  },
  {
    "prize": "best_film",
    "year": 2008,
    "th": 45,
    "film_name_zh": "投名狀",
    "film_name_en": "The Warlords",
    "atmovie_link": "http://app2.atmovies.com.tw/film/fvch20913968/",
    "imdb_link": "https://www.imdb.com/title/tt0913968",
    "movie_id": "tt0913968",
    "poster_path": "/pFSZt5JIvOVeAPYuAORR2UUcqrP.jpg"
  },
  {
    "prize": "best_film",
    "year": 2013,
    "th": 50,
    "film_name_zh": "爸媽不在家",
    "film_name_en": "Ilo Ilo",
    "atmovie_link": "http://app2.atmovies.com.tw/film/fisg52901736/",
    "imdb_link": "https://www.imdb.com/title/tt2901736",
    "movie_id": "tt2901736",
    "poster_path": "/AfVMrZHiZQW8ONm6Rok3afvHbXB.jpg"
  },
  {
    "prize": "best_film",
    "year": 2011,
    "th": 48,
    "film_name_zh": "賽德克．巴萊",
    "film_name_en": "Seediq Bale",
    "atmovie_link": "http://app2.atmovies.com.tw/film/fstw79905171/",
    "imdb_link": "https://www.imdb.com/title/tt2007993",
    "movie_id": "tt2007993",
    "poster_path": "/3ZBRh8FRQnsb36YgnpmzU0x7ebJ.jpg"
  },
  {
    "prize": "best_film",
    "year": 2010,
    "th": 47,
    "film_name_zh": "當愛來的時候",
    "film_name_en": "When Love Comes",
    "atmovie_link": "http://app2.atmovies.com.tw/film/f1tw69809021/",
    "imdb_link": "https://www.imdb.com/title/tt1829658",
    "movie_id": "tt1829658",
    "poster_path": "/v9AwrbIpJLSR2tJLh3cByLDxsc7.jpg"
  },
  {
    "prize": "best_film",
    "year": 1983,
    "th": 20,
    "film_name_zh": "小畢的故事",
    "film_name_en": "Growing Up",
    "atmovie_link": "http://app2.atmovies.com.tw/film/fVcmb5050427",
    "imdb_link": "https://www.imdb.com/title/tt00085695/",
    "movie_id": "tt00085695"
  },
  {
    "prize": "best_film",
    "year": 1995,
    "th": 32,
    "film_name_zh": "女人四十",
    "film_name_en": "Woman",
    "atmovie_link": "http://app2.atmovies.com.tw/film/fSatm0854028/",
    "imdb_link": "https://www.imdb.com/title/tt0111767",
    "movie_id": "tt0111767",
    "poster_path": "/qUDf6egeJjX5tuX5tAXWv4temBs.jpg"
  },
  {
    "prize": "best_film",
    "year": 1996,
    "th": 33,
    "film_name_zh": "陽光燦爛的日子",
    "film_name_en": "IN THE HEART OF THE SUN",
    "atmovie_link": "http://app2.atmovies.com.tw/film/fUcmb9093783/",
    "imdb_link": "https://www.imdb.com/title/tt0111786",
    "movie_id": "tt0111786",
    "poster_path": "/nu2XXY1B1VTHpmhxyuSpf7OHqxD.jpg"
  },
  {
    "prize": "best_film",
    "year": 1969,
    "th": 7,
    "film_name_zh": "小鎮春回",
    "film_name_en": "",
    "atmovie_link": "",
    "imdb_link": "",
    "movie_id": ""
  },
  {
    "prize": "best_film",
    "year": 1973,
    "th": 11,
    "film_name_zh": "忍",
    "film_name_en": "",
    "atmovie_link": "",
    "imdb_link": "",
    "movie_id": ""
  },
  {
    "prize": "best_film",
    "year": 1968,
    "th": 6,
    "film_name_zh": "路",
    "film_name_en": "The Road",
    "atmovie_link": "",
    "imdb_link": "",
    "movie_id": ""
  },
  {
    "prize": "best_film",
    "year": 2018,
    "th": 55,
    "film_name_zh": "大象席地而坐",
    "film_name_en": "An Elephant Sitting Still",
    "atmovie_link": "http://app2.atmovies.com.tw/film/fdcn68020896/",
    "imdb_link": "https://www.imdb.com/title/tt8020896",
    "movie_id": "tt8020896",
    "poster_path": "/bJfkDnsY9z9ohWdyzyCAqYZxbnS.jpg"
  },
  {
    "prize": "best_film",
    "year": 1992,
    "th": 29,
    "film_name_zh": "無言的山丘",
    "film_name_en": "Hill of No Return",
    "atmovie_link": "http://app2.atmovies.com.tw/film/fJcmb5052503/",
    "imdb_link": "https://www.imdb.com/title/tt0108602",
    "movie_id": "tt0108602",
    "poster_path": "/nf3gAZI9KAOFLXURzGHEc34yoOv.jpg"
  },
  {
    "prize": "best_film",
    "year": 1963,
    "th": 2,
    "film_name_zh": "梁山伯與祝英台The Love Eterne",
    "film_name_en": "",
    "atmovie_link": "",
    "imdb_link": "https://www.imdb.com/title/tt00057248/",
    "movie_id": "tt00057248"
  },
  {
    "prize": "best_film",
    "year": 2000,
    "th": 37,
    "film_name_zh": "臥虎藏龍",
    "film_name_en": "Crouching Tiger, Hidden Dragon",
    "atmovie_link": "http://app2.atmovies.com.tw/film/fCatm0894037/",
    "imdb_link": "https://www.imdb.com/title/tt0190332",
    "movie_id": "tt0190332",
    "poster_path": "/tKqJ6yWtOnTbiA2uzac2gejDqpI.jpg"
  },
  {
    "prize": "best_film",
    "year": 2017,
    "th": 54,
    "film_name_zh": "血觀音",
    "film_name_en": "The Bold The Corrupt and the Beautiful",
    "atmovie_link": "http://app2.atmovies.com.tw/film/fbcn35417212/",
    "imdb_link": "https://www.imdb.com/title/tt7479784",
    "movie_id": "tt7479784",
    "poster_path": "/rlhZfsmfNWKjp9yOsHV0TPUhDWu.jpg"
  },
  {
    "prize": "best_film",
    "year": 1993,
    "th": 30,
    "film_name_zh": "囍宴",
    "film_name_en": "The Wedding Banquet",
    "atmovie_link": "http://app2.atmovies.com.tw/film/fWatm0872069/",
    "imdb_link": "https://www.imdb.com/title/tt0107156",
    "movie_id": "tt0107156",
    "poster_path": "/oUloV0P1G38G1Uw09vNWk4kSssT.jpg"
  },
  {
    "prize": "best_film",
    "year": 2016,
    "th": 53,
    "film_name_zh": "八月",
    "film_name_en": "The Summer Is Gone",
    "atmovie_link": "http://app2.atmovies.com.tw/film/ftcn27057654/",
    "imdb_link": "https://www.imdb.com/title/tt6118258",
    "movie_id": "tt6118258",
    "poster_path": "/eP7lrS5l9kN5ypSWuyoJxOqd6cc.jpg"
  },
  {
    "prize": "best_film",
    "year": 2014,
    "th": 51,
    "film_name_zh": "推拿",
    "film_name_en": "Blind Massage",
    "atmovie_link": "http://app2.atmovies.com.tw/film/fbch23469964/",
    "imdb_link": "https://www.imdb.com/title/tt3469964",
    "movie_id": "tt3469964",
    "poster_path": "/1w850SIAa68TGTrRC0q3UEBR65y.jpg"
  }
]
